fortune_lite/__init__.py
fortune_lite/fortune.db
fortune_lite-1.0.1.data/scripts/fortune
fortune_lite-1.0.1.dist-info/LICENSE
fortune_lite-1.0.1.dist-info/METADATA
fortune_lite-1.0.1.dist-info/WHEEL
fortune_lite-1.0.1.dist-info/top_level.txt
fortune_lite-1.0.1.dist-info/RECORD
