Metadata-Version: 2.1
Name: fortune-lite
Version: 1.0.1
Summary: A Python implementation of fortune
Home-page: https://github.com/buck-ross/fortune_lite
Author: Buckley Ross
Author-email: buckleyross42@gmail.com
License: Apache 2.0
Platform: UNKNOWN
